[{"blur":"images/hsz/1_blur.txt","thumb":"images/hsz/1_thumb.webp","full":"images/hsz/1_full.webp"},{"blur":"images/hsz/10_blur.txt","thumb":"images/hsz/10_thumb.webp","full":"images/hsz/10_full.webp"},{"blur":"images/hsz/11_blur.txt","thumb":"images/hsz/11_thumb.webp","full":"images/hsz/11_full.webp"},{"blur":"images/hsz/12_blur.txt","thumb":"images/hsz/12_thumb.webp","full":"images/hsz/12_full.webp"},{"blur":"images/hsz/13_blur.txt","thumb":"images/hsz/13_thumb.webp","full":"images/hsz/13_full.webp"},{"blur":"images/hsz/14_blur.txt","thumb":"images/hsz/14_thumb.webp","full":"images/hsz/14_full.webp"},{"blur":"images/hsz/15_blur.txt","thumb":"images/hsz/15_thumb.webp","full":"images/hsz/15_full.webp"},{"blur":"images/hsz/16_blur.txt","thumb":"images/hsz/16_thumb.webp","full":"images/hsz/16_full.webp"},{"blur":"images/hsz/17_blur.txt","thumb":"images/hsz/17_thumb.webp","full":"images/hsz/17_full.webp"},{"blur":"images/hsz/18_blur.txt","thumb":"images/hsz/18_thumb.webp","full":"images/hsz/18_full.webp"},{"blur":"images/hsz/19_blur.txt","thumb":"images/hsz/19_thumb.webp","full":"images/hsz/19_full.webp"},{"blur":"images/hsz/2_blur.txt","thumb":"images/hsz/2_thumb.webp","full":"images/hsz/2_full.webp"},{"blur":"images/hsz/20_blur.txt","thumb":"images/hsz/20_thumb.webp","full":"images/hsz/20_full.webp"},{"blur":"images/hsz/21_blur.txt","thumb":"images/hsz/21_thumb.webp","full":"images/hsz/21_full.webp"},{"blur":"images/hsz/22_blur.txt","thumb":"images/hsz/22_thumb.webp","full":"images/hsz/22_full.webp"},{"blur":"images/hsz/23_blur.txt","thumb":"images/hsz/23_thumb.webp","full":"images/hsz/23_full.webp"},{"blur":"images/hsz/24_blur.txt","thumb":"images/hsz/24_thumb.webp","full":"images/hsz/24_full.webp"},{"blur":"images/hsz/25_blur.txt","thumb":"images/hsz/25_thumb.webp","full":"images/hsz/25_full.webp"},{"blur":"images/hsz/26_blur.txt","thumb":"images/hsz/26_thumb.webp","full":"images/hsz/26_full.webp"},{"blur":"images/hsz/27_blur.txt","thumb":"images/hsz/27_thumb.webp","full":"images/hsz/27_full.webp"},{"blur":"images/hsz/28_blur.txt","thumb":"images/hsz/28_thumb.webp","full":"images/hsz/28_full.webp"},{"blur":"images/hsz/29_blur.txt","thumb":"images/hsz/29_thumb.webp","full":"images/hsz/29_full.webp"},{"blur":"images/hsz/3_blur.txt","thumb":"images/hsz/3_thumb.webp","full":"images/hsz/3_full.webp"},{"blur":"images/hsz/30_blur.txt","thumb":"images/hsz/30_thumb.webp","full":"images/hsz/30_full.webp"},{"blur":"images/hsz/31_blur.txt","thumb":"images/hsz/31_thumb.webp","full":"images/hsz/31_full.webp"},{"blur":"images/hsz/32_blur.txt","thumb":"images/hsz/32_thumb.webp","full":"images/hsz/32_full.webp"},{"blur":"images/hsz/33_blur.txt","thumb":"images/hsz/33_thumb.webp","full":"images/hsz/33_full.webp"},{"blur":"images/hsz/34_blur.txt","thumb":"images/hsz/34_thumb.webp","full":"images/hsz/34_full.webp"},{"blur":"images/hsz/35_blur.txt","thumb":"images/hsz/35_thumb.webp","full":"images/hsz/35_full.webp"},{"blur":"images/hsz/36_blur.txt","thumb":"images/hsz/36_thumb.webp","full":"images/hsz/36_full.webp"},{"blur":"images/hsz/37_blur.txt","thumb":"images/hsz/37_thumb.webp","full":"images/hsz/37_full.webp"},{"blur":"images/hsz/38_blur.txt","thumb":"images/hsz/38_thumb.webp","full":"images/hsz/38_full.webp"},{"blur":"images/hsz/39_blur.txt","thumb":"images/hsz/39_thumb.webp","full":"images/hsz/39_full.webp"},{"blur":"images/hsz/4_blur.txt","thumb":"images/hsz/4_thumb.webp","full":"images/hsz/4_full.webp"},{"blur":"images/hsz/40_blur.txt","thumb":"images/hsz/40_thumb.webp","full":"images/hsz/40_full.webp"},{"blur":"images/hsz/41_blur.txt","thumb":"images/hsz/41_thumb.webp","full":"images/hsz/41_full.webp"},{"blur":"images/hsz/42_blur.txt","thumb":"images/hsz/42_thumb.webp","full":"images/hsz/42_full.webp"},{"blur":"images/hsz/43_blur.txt","thumb":"images/hsz/43_thumb.webp","full":"images/hsz/43_full.webp"},{"blur":"images/hsz/44_blur.txt","thumb":"images/hsz/44_thumb.webp","full":"images/hsz/44_full.webp"},{"blur":"images/hsz/45_blur.txt","thumb":"images/hsz/45_thumb.webp","full":"images/hsz/45_full.webp"},{"blur":"images/hsz/46_blur.txt","thumb":"images/hsz/46_thumb.webp","full":"images/hsz/46_full.webp"},{"blur":"images/hsz/47_blur.txt","thumb":"images/hsz/47_thumb.webp","full":"images/hsz/47_full.webp"},{"blur":"images/hsz/48_blur.txt","thumb":"images/hsz/48_thumb.webp","full":"images/hsz/48_full.webp"},{"blur":"images/hsz/49_blur.txt","thumb":"images/hsz/49_thumb.webp","full":"images/hsz/49_full.webp"},{"blur":"images/hsz/5_blur.txt","thumb":"images/hsz/5_thumb.webp","full":"images/hsz/5_full.webp"},{"blur":"images/hsz/50_blur.txt","thumb":"images/hsz/50_thumb.webp","full":"images/hsz/50_full.webp"},{"blur":"images/hsz/51_blur.txt","thumb":"images/hsz/51_thumb.webp","full":"images/hsz/51_full.webp"},{"blur":"images/hsz/52_blur.txt","thumb":"images/hsz/52_thumb.webp","full":"images/hsz/52_full.webp"},{"blur":"images/hsz/53_blur.txt","thumb":"images/hsz/53_thumb.webp","full":"images/hsz/53_full.webp"},{"blur":"images/hsz/54_blur.txt","thumb":"images/hsz/54_thumb.webp","full":"images/hsz/54_full.webp"},{"blur":"images/hsz/55_blur.txt","thumb":"images/hsz/55_thumb.webp","full":"images/hsz/55_full.webp"},{"blur":"images/hsz/56_blur.txt","thumb":"images/hsz/56_thumb.webp","full":"images/hsz/56_full.webp"},{"blur":"images/hsz/57_blur.txt","thumb":"images/hsz/57_thumb.webp","full":"images/hsz/57_full.webp"},{"blur":"images/hsz/58_blur.txt","thumb":"images/hsz/58_thumb.webp","full":"images/hsz/58_full.webp"},{"blur":"images/hsz/59_blur.txt","thumb":"images/hsz/59_thumb.webp","full":"images/hsz/59_full.webp"},{"blur":"images/hsz/6_blur.txt","thumb":"images/hsz/6_thumb.webp","full":"images/hsz/6_full.webp"},{"blur":"images/hsz/60_blur.txt","thumb":"images/hsz/60_thumb.webp","full":"images/hsz/60_full.webp"},{"blur":"images/hsz/61_blur.txt","thumb":"images/hsz/61_thumb.webp","full":"images/hsz/61_full.webp"},{"blur":"images/hsz/62_blur.txt","thumb":"images/hsz/62_thumb.webp","full":"images/hsz/62_full.webp"},{"blur":"images/hsz/63_blur.txt","thumb":"images/hsz/63_thumb.webp","full":"images/hsz/63_full.webp"},{"blur":"images/hsz/7_blur.txt","thumb":"images/hsz/7_thumb.webp","full":"images/hsz/7_full.webp"},{"blur":"images/hsz/8_blur.txt","thumb":"images/hsz/8_thumb.webp","full":"images/hsz/8_full.webp"},{"blur":"images/hsz/9_blur.txt","thumb":"images/hsz/9_thumb.webp","full":"images/hsz/9_full.webp"}]